tiffslide_xarray/__init__.py
tiffslide_xarray/_version.py
tiffslide_xarray/accessors.py
tiffslide_xarray/attrs.py
tiffslide_xarray/data.py
tiffslide_xarray/grid.py
tiffslide_xarray/intake.py
tiffslide_xarray-0.3.0.dist-info/LICENSE
tiffslide_xarray-0.3.0.dist-info/METADATA
tiffslide_xarray-0.3.0.dist-info/WHEEL
tiffslide_xarray-0.3.0.dist-info/entry_points.txt
tiffslide_xarray-0.3.0.dist-info/RECORD
