Metadata-Version: 2.3
Name: tiffslide_xarray
Version: 0.3.0
Summary: Xarray extension that uses xarray to lazy read 2D Tiff files.
Keywords: tiffslide,xarray
Author: S. Joshua Swamidass
Author-email: swamidass@gmail.com
Requires-Python: >=3.10,<4.0
Classifier: Development Status :: 3 - Alpha
Classifier: License :: OSI Approved :: BSD License
Classifier: Programming Language :: Python :: 3
Classifier: Programming Language :: Python :: 3.10
Classifier: Programming Language :: Python :: 3.11
Classifier: Programming Language :: Python :: 3.12
Classifier: Programming Language :: Python :: 3.13
Classifier: Programming Language :: Python :: 3.9
Classifier: Topic :: Scientific/Engineering :: Artificial Intelligence
Classifier: Topic :: Scientific/Engineering :: Bio-Informatics
Classifier: Topic :: Scientific/Engineering :: Image Processing
Classifier: Topic :: Scientific/Engineering :: Medical Science Apps.
Requires-Dist: dm-tree (==0.1.8)
Requires-Dist: envsubst (>=0.1.5)
Requires-Dist: frozendict (>=2.4.6,<3.0.0)
Requires-Dist: numpy (>=2)
Requires-Dist: pydantic (>=2.4.2)
Requires-Dist: ruamel-yaml (>=0.18.5)
Requires-Dist: tiffslide (>=2.2.0)
Requires-Dist: xarray (>=2024.10)
Project-URL: Homepage, https://github.com/swamidasslab/tiffslide-xarray
Project-URL: Repository, https://github.com/swamidasslab/tiffslide-xarray
